Workbook

Sheet Dashboard
A1: GreenChainz B2B Marketplace — Intelligence Dashboard
A2: Sustainable Building Materials · Supplier Targets · Decision Maker Roles · Outreach Intelligence
A4: SUPPLIER TARGETS | D4: SUPPLIERS BY CATEGORY | G4: ROLES BY PROCUREMENT LAYER
A5: Total Suppliers | B5: =COUNTA('Supplier Targets'!A2:A1000) -> 134 | D5: Circular Economy / Waste | E5: =COUNTIF('Supplier Targets'!B2:B1000,"Circular Economy / Waste") -> 26 | G5: Design Authorities | H5: =COUNTIF('Decision Maker Roles'!B2:B1000,"Design Authorities") -> 6
A6: Have EPD | B6: =COUNTIF('Supplier Targets'!G2:G1000,"yes") -> 28 | D6: Concrete / Cement | E6: =COUNTIF('Supplier Targets'!B2:B1000,"Concrete / Cement") -> 20 | G6: Financial Gatekeepers | H6: =COUNTIF('Decision Maker Roles'!B2:B1000,"Financial Gatekeepers") -> 5
A7: High Readiness | B7: =COUNTIF('Supplier Targets'!H2:H1000,"high") -> 57 | D7: Wood / Timber | E7: =COUNTIF('Supplier Targets'!B2:B1000,"Wood / Timber") -> 14 | G7: Execution Tier | H7: =COUNTIF('Decision Maker Roles'!B2:B1000,"Execution Tier") -> 6
A8: Medium Readiness | B8: =COUNTIF('Supplier Targets'!H2:H1000,"medium") -> 60 | D8: Mass Timber | E8: =COUNTIF('Supplier Targets'!B2:B1000,"Mass Timber") -> 10 | G8: Operational Stewards | H8: =COUNTIF('Decision Maker Roles'!B2:B1000,"Operational Stewards") -> 4
A9: Low Readiness | B9: =COUNTIF('Supplier Targets'!H2:H1000,"low") -> 17 | D9: Insulation / Bio-Based | E9: =COUNTIF('Supplier Targets'!B2:B1000,"Insulation / Bio-Based") -> 9 | G9: Strategic Leadership | H9: =COUNTIF('Decision Maker Roles'!B2:B1000,"Strategic Leadership") -> 4
D10: Insulation | E10: =COUNTIF('Supplier Targets'!B2:B1000,"Insulation") -> 10 | G10: Sector Verticals | H10: =COUNTIF('Decision Maker Roles'!B2:B1000,"Sector Verticals") -> 8
A11: DECISION MAKER ROLES | D11: Mycelium / Bio-Fabrication | E11: =COUNTIF('Supplier Targets'!B2:B1000,"Mycelium / Bio-Fabrication") -> 10 | G11: Supply Chain | H11: =COUNTIF('Decision Maker Roles'!B2:B1000,"Supply Chain") -> 5
A12: Total Roles Profiled | B12: =COUNTA('Decision Maker Roles'!A2:A1000) -> 38 | D12: Glazing / Windows | E12: =COUNTIF('Supplier Targets'!B2:B1000,"Glazing / Windows") -> 5
A13: Hidden Gem Roles | B13: =COUNTIF('Decision Maker Roles'!G2:G1000,"yes") -> 13 | D13: Glazing / Curtain Wall | E13: =COUNTIF('Supplier Targets'!B2:B1000,"Glazing / Curtain Wall") -> 4
A14: High Purchase Volume | B14: =COUNTIF('Decision Maker Roles'!F2:F1000,"high") -> 19 | D14: Acoustic / Lighting | E14: =COUNTIF('Supplier Targets'!B2:B1000,"Acoustic / Lighting") -> 5
D15: Marine / Algae Materials | E15: =COUNTIF('Supplier Targets'!B2:B1000,"Marine / Algae Materials") -> 5
A16: TARGET FIRMS | D16: Biophilic / Living Systems | E16: =COUNTIF('Supplier Targets'!B2:B1000,"Biophilic / Living Systems") -> 6
A17: Total Target Firms | B17: =COUNTA('Target Firms'!A2:A1000) -> 14 | D17: Other | E17: =B5-SUM(E5:E16) -> 10
A20: QUICK REFERENCE — TOP PRIORITY TARGETS
A21: Priority | B21: Supplier / Company | C21: Category | D21: Pitch Angle | E21: EPD
A22: 1 — Founding 50 | B22: Prometheus Materials | C22: Bio-Cement | D22: Specification Security — ASTM compliance data + bio-cool factor | E22: Unknown
A23: 1 — Founding 50 | B23: SmartLam North America | C23: CLT / Mass Timber | D23: Sell Speed — schedule savings of CLT vs. concrete | E23: Yes
A24: 1 — Founding 50 | B24: Hempitecture | C24: Hemp Insulation | D24: Health & Safety — no itch, no VOC, carbon storage | E24: Unknown
A25: 1 — Founding 50 | B25: StoneCycling | C25: Waste-Based Bricks | D25: Site-Specific Circularity — demolition waste to new bricks | E25: Unknown
A26: 1 — Founding 50 | B26: TimberHP | C26: Wood Fiber Insulation | D26: Domestic Wood Fiber — first North American producer, no import lead time | E26: Unknown
A28: KEY ENGAGEMENT INSIGHT
A29: Hidden Gem Roles to prioritize: Specification Writer, Landscape Architect, Value Engineer, Drywall Subcontractor, Flooring Subcontractor, Concrete Subcontractor, Superintendent, Facility Manager, Energy Manager, Cleaning Manager, Infection Control Officer, Fire Marshal
A30: These under-served roles have high influence but are overlooked by most sustainable material vendors — ideal GreenChainz differentiation opportunity.
D37: 💡 See charts on Supplier Targets and Decision Maker Roles tabs for visual breakdowns

Sheet Decision Maker Roles
A1: Role Title | B1: Procurement Layer | C1: Decision Driver | D1: Data Needs | E1: Engagement Hook | F1: Purchase Volume | G1: Hidden Gem | I1: Procurement Layer | J1: Count
A2: Architect of Record (AOR) | B2: Design Authorities | C2: Liability & Code Compliance | D2: EPDs, HPDs, LCA, fire-rating data, VOC test results, code compliance documentation | E2: Lead with liability elimination and code compliance proof; provide Red List-free documentation; emphasize protection from Toxic Tort litigation | F2: high | G2: no | I2: Design Authorities | J2: 6
A3: Project Architect (PA) | B3: Design Authorities | C3: Liability & Code Compliance | D3: EPDs, HPDs, fire-rating data, performance specs, code compliance documentation | E3: Same as AOR — position sustainable materials as risk-reduction tools not green choices; provide code-compliant spec language | F3: high | G3: no | I3: Financial Gatekeepers | J3: 5
A4: Specification Writer | B4: Design Authorities | C4: Defensibility & Data | D4: ASTM/ISO test reports, LCA, EPDs, California CDPH VOC compliance, third-party certifications, chain-of-custody docs | E4: Supply complete third-party verified documentation; offer pre-written spec language and 'No Substitution' clause language; make documentation turnkey | F4: high | G4: yes | I4: Execution Tier | J4: 6
A5: LEED AP / Sustainability Consultant | B5: Design Authorities | C5: The Point System | D5: EPDs, HPDs, chain-of-custody certifications, LEED Materials & Resources credit documentation, third-party verified data | E5: Lead with LEED/BREEAM/WELL credit contribution math; provide pre-formatted documentation packages; reduce their documentation workload | F5: high | G5: no | I5: Operational Stewards | J5: 4
A6: Interior Designer (Commercial/Contract) | B6: Design Authorities | C6: Occupant Health & Productivity | D6: Indoor air quality data, antimicrobial certifications, acoustic performance ratings, recycled content documentation, WELL certification data | E6: Position as wellness and talent-retention plays; offer 'building standard' package specs; emphasize biophilic and acoustic performance | F6: high | G6: no | I6: Strategic Leadership | J6: 4
A7: Landscape Architect | B7: Design Authorities | C7: Site Water Management & Heat Island Compliance | D7: Permeability ratings, stormwater retention data, albedo/reflectivity specs, recycled aggregate content, municipal code compliance docs | E7: Frame as cost-saving civil engineering solution eliminating underground retention tanks; cite local stormwater fee savings and Heat Island ordinance compliance | F7: medium | G7: yes | I7: Sector Verticals | J7: 8
A8: Quantity Surveyor (QS) / Cost Consultant | B8: Financial Gatekeepers | C8: Whole Life Costing & Carbon Accounting | D8: NPV/lifecycle cost models, carbon accounting data, durability/warranty data, carbon budget compliance reports | E8: Lead with ROI models and Whole Life Cost analysis; provide carbon budget data; position as the tool that wins Value Engineering battles | F8: high | G8: no | I8: Supply Chain | J8: 5
A9: Value Engineer (VE) | B9: Financial Gatekeepers | C9: System Deletion & Labor Reduction | D9: Function-per-dollar data, trade elimination potential, labor cost comparisons, multifunctionality specs | E9: Never pitch 'green'; pitch 'simplification' and 'labor reduction'; show how one material replaces multiple systems/trades (e.g. SIPs) | F9: medium | G9: yes
A10: Insurance Risk Manager / Underwriter | B10: Financial Gatekeepers | C10: Loss Prevention & Resilience | D10: Mold resistance ratings, fire resistance data, extreme weather performance data, actuarial risk reduction metrics | E10: Market materials as 'Risk Reduction Assets'; provide data showing premium-reduction potential; position CLT and mineral wool as safety-correlated sustainability | F10: medium | G10: yes
A11: Asset Manager (Real Estate) | B11: Financial Gatekeepers | C11: Liquidity & Stranded Asset Prevention | D11: ESG compliance documentation, energy performance data, retrofit ROI, NYC Local Law 97 and similar regulatory compliance | E11: Frame materials as stranded-asset prevention tools; show how green retrofits maintain institutional buyer eligibility and protect exit strategy | F11: high | G11: no
A12: Real Estate Appraiser / Valuer | B12: Financial Gatekeepers | C12: Market Valuation & Cap Rates | D12: Cap rate comparisons, NOI improvement data, green building valuation premiums, market transaction data | E12: Position as the validation layer that unlocks developer financing; provide market data on green building valuation premiums | F12: low | G12: no
A13: Project Manager (General Contractor) | B13: Execution Tier | C13: Schedule & Site Safety | D13: Lead times, installation speed data, waste take-back programs, VOC safety data sheets, waste diversion compliance docs | E13: Lead with schedule acceleration and job-site safety; offer take-back programs; emphasize low-VOC and dust-free installation keeping the job moving | F13: high | G13: no
A14: Drywall / Framing Subcontractor | B14: Execution Tier | C14: Labor Productivity & Ergonomics | D14: Weight specs, dust ratings, score-and-snap performance data, consistency/defect rates, callback rate data | E14: Pitch labor savings and crew ergonomics; demo lighter boards and cleaner cuts; provide consistency data showing reduced callbacks | F14: high | G14: yes
A15: Flooring Subcontractor | B15: Execution Tier | C15: Moisture Mitigation & Bond Failure Prevention | D15: Moisture tolerance specs, adhesive requirements, breathability ratings, VOC levels of adhesives, installation speed data | E15: Lead with bond failure risk reduction; highlight adhesive-free or low-adhesive systems; emphasize worker protection from toxic fumes | F15: high | G15: yes
A16: Concrete Subcontractor | B16: Execution Tier | C16: Workability & Cure Time | D16: Mix workability/flow data, cure time specs, fly ash/slag blend ratios, pump performance data, carbon content of mixes | E16: Lead with workability and pour-labor savings; position low-carbon mixes as technically superior; provide mix performance data | F16: high | G16: yes
A17: Procurement Specialist / Purchasing Agent | B17: Execution Tier | C17: Supply Chain Security & Price Stability | D17: Local sourcing documentation, LEED local material credit data, lead times, pricing stability data, supplier reliability data | E17: Lead with supply chain resilience narrative; emphasize domestic sourcing for delivery certainty; provide LEED credit documentation as bonus | F17: high | G17: no
A18: Superintendent (The Super) | B18: Execution Tier | C18: Defect Reduction & Constructability | D18: Consistency/defect rate data, dimensional stability specs, punch-list performance data | E18: Show how sustainable composites eliminate warping and reduce punch-list repairs; lead with site-level headache elimination | F18: medium | G18: yes
A19: Facility Manager (FM) / Director of Facilities | B19: Operational Stewards | C19: Total Cost of Ownership & Maintenance Cycles | D19: TCO comparisons, maintenance cycle data, cleaning chemical requirements, durability ratings, OpEx projections | E19: Lead with reduced maintenance labor and toxic chemical elimination; provide TCO models showing durable flooring vs. VCT 40-year cost | F19: high | G19: yes
A20: Director of Workplace Experience | B20: Operational Stewards | C20: Employee Experience & Friction Reduction | D20: WELL certification data, air quality specs, biophilic design certifications, acoustic performance ratings, talent retention research | E20: Position as talent retention and culture tool; reference the 'hotelification of the office' trend; connect materials to HR recruitment metrics | F20: medium | G20: no
... A39: Fire Marshal / Code Official | B39: Supply Chain | C39: Public Safety & Code Approval | D39: Code compliance documentation, fire safety test results, mass timber approval precedents, sustainable insulation safety data | E39: Lead with code compliance and safety proof; provide approval precedents for mass timber and advanced insulation; position approval as the ultimate purchasing permit | F39: medium | G39: yes

Sheet Target Firms
A1: Firm Name | B1: Firm Type | C1: Relevant Roles | D1: Notes
A2: Gensler | B2: architecture | C2: Specification Writer, Architect of Record, Project Architect, LEED AP / Sustainability Consultant, Interior Designer | D2: Explicitly named as example of a large architectural practice employing Specification Writers with immense power over material specs. One of the world's largest architecture firms with a dedicated specs department.
A3: HOK | B3: architecture | C3: Specification Writer, Architect of Record, Project Architect, LEED AP / Sustainability Consultant, Interior Designer | D3: Explicitly named alongside Gensler as an example large architectural practice with embedded Spec Writers who control project manuals exceeding 1000 pages.
A4: AECOM | B4: architecture / engineering / construction management | C4: Specification Writer, Architect of Record, Project Architect, LEED AP / Sustainability Consultant, Quantity Surveyor, Value Engineer | D4: Explicitly named as example of large architectural/engineering practice employing Specification Writers. Also operates as a major GC/CM firm covering multiple procurement layers.
A5: University of Tampa | B5: higher education | C5: University Campus Planner | D5: Referenced in citations (ZipRecruiter job listing) as employer of Campus Planner role. Long-horizon 100-year campus procurement decision-maker.
A6: Florida State University | B6: higher education | C6: University Campus Planner | D6: Referenced in citations (ZipRecruiter job listing) as employer of Campus Planner role. Campus planners select durable slate roofs and stone facades on 100-year lifecycle basis.
A7: Northeastern University | B7: higher education | C7: University Campus Planner | D7: Referenced in citations (Career.com job listing) as employer of Campus Planner role in Boston MA.
A8: Estee Lauder Companies (MAC) | B8: retail / consumer goods | C8: Visual Merchandising Director, Chief Marketing Officer / Brand Director, Store Planning Director | D8: Referenced in citations as employer of Global Visual Merchandising & Retail Experience Director at MAC brand. CMO/Brand Directors at consumer brands mandate recycled materials to align physical stores with sustainability brand narrative.
A9: MCM (MCM Worldwide) | B9: retail / luxury goods | C9: Visual Merchandising Director, Chief Marketing Officer / Brand Director, Store Planning Director | D9: Referenced in citations via MCM 2022 Sustainability Report. Retail brands with sustainability commitments are key targets for sustainable fixture and display materials.
A10: Primark Stores Limited | B10: retail | C10: Franchisee / Store Planning Director, Visual Merchandising Director | D10: Referenced in citations (Franchise Design Manager role listing). Retail chains with franchise models are targets for sustainable modular fixture systems.
A11: JPMorgan Chase | B11: financial services / real estate finance | C11: Affordable Housing Developer, Asset Manager, Chief Procurement Officer | D11: Referenced in citations regarding affordable housing financing. Financial institutions funding LIHTC affordable housing projects are indirect but powerful drivers of sustainable material selection through developer client requirements.
A12: Intrepid Group | B12: corporate / consulting | C12: Chief People Officer (CHRO) / HR Director | D12: Referenced via citation (TechFinitive article on Alex Png as CPO of Intrepid Group). Companies with HR-driven workplace design strategies are targets for wellness-oriented sustainable materials.
... A15: Areim | B15: real estate asset management | C15: Asset Manager, Chief Sustainability Officer | D15: Referenced in citations (Areim sustainability page). Real estate asset management firms with ESG mandates are key Asset Manager targets for sustainable retrofit materials.

Sheet Supplier Targets
A1: Company Name | B1: Category | C1: Subcategory | D1: Location | E1: Key Product | F1: GreenChainz Pitch Angle | G1: Has EPD | H1: Readiness Level | I1: Notes | J1: Source | L1: Category | M1: Count
A2: Prometheus Materials | B2: Concrete / Cement | C2: Bio-Cement | D2: Colorado, USA | E2: ProZERO (algae bio-cement / precast CMU blocks) | F2: Specification Security — present ASTM compliance data alongside the 'cool factor' to bypass engineer fear of biological degradation | G2: unknown | H2: high | I2: University of Colorado Boulder spin-off; uses microalgae to produce bio-cement; transitioning from 'science project' to 'standard spec'; prime Founding 50 target | J2: Ecosystem Analysis PDF | L2: Circular Economy / Waste | M2: 26
A3: Biomason | B3: Concrete / Cement | C3: Bio-Cement | D3: North Carolina, USA | E3: Biolith tiles (bacterial cement grown at ambient temperature) | F3: From Niche to Norm — find early-adopter architects (HOK, Gensler) willing to specify bio-based materials for non-structural applications as gateway to structural use | G3: unknown | H3: high | I3: Grows cement using Sporosarcina pasteurii bacteria; commercial applications in tiles/pavers/facades; challenge is scaling to structural | J3: Ecosystem Analysis PDF | L3: Concrete / Cement | M3: 20
A4: Brimstone | B4: Concrete / Cement | C4: Low-Carbon Portland Cement | D4: California, USA | E4: Zero-carbon Portland cement from calcium silicate rocks (chemically identical to OPC) | F4: Drop-in Replacement — intercept specs for 'Portland Cement Type I/II' and flag Brimstone as functionally identical but carbon-superior; no re-engineering required | G4: unknown | H4: high | I4: Process creates no process emissions; yields magnesium byproduct that actively absorbs CO2; massive selling point for risk-averse structural engineers | J4: Ecosystem Analysis PDF | L4: Wood / Timber | M4: 14
A5: Fortera | B5: Concrete / Cement | C5: Carbon-Captured Cementitious Material | D5: California, USA | E5: ReCarb (CO2-mineralized supplementary cementitious material) | F5: The Carbon Sink — position ReCarb as a carbon removal credit for Net Zero certification | G5: unknown | H5: high | I5: Intercepts CO2 from existing cement plant flues; blends into cement lowering GWP by 10-60% | J5: Ecosystem Analysis PDF | L5: Mass Timber | M5: 10
A6: Sublime Systems | B6: Concrete / Cement | C6: Electrochemical Cement | D6: Massachusetts, USA | E6: Electrochemically produced cement (ambient temperature, fossil-fuel-free) | F6: Deep Tech to Spec Language — translate electrochemical advantages into simple 'Carbon Saved per Ton' metrics | G6: unknown | H6: medium | I6: MIT spin-off; high technical credibility but low market penetration vs. giants like Holcim | J6: Ecosystem Analysis PDF | L6: Insulation / Bio-Based | M6: 9
A7: Geopolymer Solutions | B7: Concrete / Cement | C7: Geopolymer | D7: Illinois, USA | E7: Cold Fusion Concrete (geopolymer, acid/salt/heat resistant) | F7: Durability as Sustainability — showcase aesthetic/sustainability benefits; move from petrochemical/industrial to commercial | G7: unknown | H7: medium | I7: Historically targets industrial applications; needs platform to break into high-end residential and commercial | J7: Ecosystem Analysis PDF | L7: Insulation | M7: 10
A8: Wagners | B8: Concrete / Cement | C8: Geopolymer | D8: Australia / Global | E8: Earth Friendly Concrete (EFC) — zero Portland cement geopolymer | F8: Vertical Built Environment — expand from horizontal infrastructure to vertical building construction | G8: unknown | H8: high | I8: Proven success in major infrastructure (Brisbane West Wellcamp Airport); needs spec channel into vertical buildings | J8: Ecosystem Analysis PDF | L8: Mycelium / Bio-Fabrication | M8: 10
A9: Urban Mining CT | B9: Concrete / Cement | C9: Recycled Glass Pozzolan | D9: Connecticut, USA | E9: Pozzotive (high-performance pozzolan from 100% recycled post-consumer glass) | F9: Hyper-Local Circularity — geo-target Northeast US architects; flag double LEED credit for NYC/Boston projects | G9: unknown | H9: high | I9: Solves waste glass crisis + reduces concrete carbon footprint simultaneously; strong LEED play for regional projects | J9: Ecosystem Analysis PDF | L9: Glazing / Windows | M9: 5
A10: C-Crete Technologies | B10: Concrete / Cement | C10: Ceramic Concrete | D10: California, USA | E10: Ceramic-like Portland-cement-free concrete (pourable like traditional concrete) | F10: Zero-Training Transition — crews need no new pouring techniques; removes major barrier to novel material adoption | G10: unknown | H10: medium | I10: Targets hard-to-abate sector; no new workforce training required is key selling point | J10: Ecosystem Analysis PDF | L10: Biophilic / Living Systems | M10: 6
A11: Blue Planet | B11: Concrete / Cement | C11: Carbon-Sequestering Aggregate | D11: California, USA | E11: CO2-mineralized limestone-coated aggregate (carbon-negative concrete aggregate) | F11: Offset Inside the Mix — aggregate as the carbon hero; allows carbon-negative concrete without changing preferred structural cement supplier | G11: unknown | H11: medium | I11: Captures CO2 from flue gas and grows limestone coating on rock particles; enables Carbon Negative Concrete without changing cement | J11: Ecosystem Analysis PDF
A12: CarbiCrete | B12: Concrete / Cement | C12: Carbon-Sequestering Precast | D12: Canada | E12: Steel slag + CO2-cured precast blocks (no Portland cement) | F12: The Precast Specialist — filter platform searches so CarbiCrete appears only for precast applications | G12: unknown | H12: high | I12: Eliminates cement entirely; uses steel slag waste; CO2 curing happens in factory (precast only) | J12: Ecosystem Analysis PDF | L12: Readiness | M12: Count
A13: Solidia Technologies | B13: Concrete / Cement | C13: CO2-Cured Concrete | D13: Texas, USA | E13: CO2-cured lightweight/strong concrete (cures by absorbing CO2 instead of water) | F13: Water-Wise Concrete — pitch to architects in drought zones (California, Arizona) as water conservation play | G13: unknown | H13: medium | I13: Curing process recovers most water; major sustainability play for water-scarce regions | J13: Ecosystem Analysis PDF | L13: High | M13: 57
A14: CarbonCure | B14: Concrete / Cement | C14: CO2 Injection Technology | D14: Nova Scotia, Canada | E14: CO2 injection technology for ready-mix concrete (reduces cement usage, strengthens concrete) | F14: Local Availability — integrate their 'producer finder' map into platform so architects find nearest plant using CarbonCure technology | G14: unknown | H14: high | I14: Technology provider, not material manufacturer; massive network of partner ready-mix plants; strong geographic play | J14: Ecosystem Analysis PDF | L14: Medium | M14: 60
A15: Eco Material Technologies | B15: Concrete / Cement | C15: Green Cement | D15: USA | E15: Green cement supplementary cementitious materials | F15: Drop-in Replacement | G15: unknown | H15: medium | I15: Listed in Master Directory Category A; Low-Carbon Concrete & Masonry | J15: Ecosystem Analysis PDF | L15: Low | M15: 17
A16: Terra CO2 | B16: Concrete / Cement | C16: Low-Carbon Cementitious | D16: USA | E16: Low-carbon cementitious materials | F16: Drop-in Replacement | G16: unknown | H16: medium | I16: Listed in Master Directory Category A; Low-Carbon Concrete & Masonry | J16: Ecosystem Analysis PDF
A17: Partanna | B17: Concrete / Cement | C17: Carbon-Negative Concrete | D17: USA | E17: Carbon-negative concrete | F17: The Carbon Sink | G17: unknown | H17: medium | I17: Listed in Master Directory Category A; carbon-negative concrete product | J17: Ecosystem Analysis PDF
A18: Hoffmann Green Cement | B18: Concrete / Cement | C18: Clinker-Free Cement | D18: France | E18: Clinker-free cement | F18: Drop-in Replacement | G18: unknown | H18: medium | I18: Listed in Master Directory Category A; clinker-free cement technology | J18: Ecosystem Analysis PDF
A19: Ecocem | B19: Concrete / Cement | C19: GGBS Cement | D19: Europe / Global | E19: GGBS (Ground Granulated Blast-furnace Slag) low-carbon cement | F19: Drop-in Replacement | G19: unknown | H19: high | I19: Listed in Master Directory Category A; GGBS supplementary cementitious material | J19: Ecosystem Analysis PDF
A20: Heidelberg Materials | B20: Concrete / Cement | C20: Low-Carbon Concrete (Transitioning Incumbent) | D20: Germany / Global | E20: EcoCrete low-carbon concrete line | F20: Sell the specific green product lines (EcoCrete) within the incumbent portfolio | G20: yes | H20: high | I20: Major incumbent transitioning to low carbon; platform approach is to surface their green product lines specifically | J20: Ecosystem Analysis PDF
A21: Holcim | B21: Concrete / Cement | C21: Low-Carbon Concrete (Transitioning Incumbent) | D21: Switzerland / Global | E21: ECOPact / ECOPlanet low-carbon concrete lines | F21: Sell the specific green product lines (ECOPact / ECOPlanet) within the incumbent portfolio | G21: yes | H21: high | I21: Major global cement incumbent; platform surfaces specifically the green product lines to specifiers | J21: Ecosystem Analysis PDF
A22: Mercer Mass Timber | B22: Mass Timber | C22: CLT / Glulam | D22: Washington / Arkansas, USA | E22: CLT and Glulam at industrial scale | F22: Capacity Optimization — connect with mid-market projects (schools, offices) to aggregate demand and optimize factory runs | G22: unknown | H22: high | I22: Large manufacturer with significant capacity; needs mid-market project volume to fill factory runs | J22: Ecosystem Analysis PDF
A23: SmartLam North America | B23: Mass Timber | C23: CLT | D23: Montana / Alabama, USA | E23: CLT panels (Cross-Laminated Timber); first commercial US CLT manufacturer | F23: Sell Speed — calculate schedule savings of CLT vs. concrete for specific project | G23: yes | H23: high | I23: First commercial US CLT manufacturer; deep history in industrial matting; SFI Chain-of-Custody certified | J23: Ecosystem Analysis PDF
A24: Binderholz | B24: Mass Timber | C24: Mass Timber / CLT | D24: Austria / USA | E24: Mass timber products (CLT, glulam, solid wood) | F24: Global Tech, Local Code — translate European certifications into US-equivalent code compliance data | G24: yes | H24: high | I24: Global European giant expanding aggressively into US; sophisticated EPDs; faces 'buy local' friction | J24: Ecosystem Analysis PDF
A25: StructureCraft | B25: Mass Timber | C25: Engineered Timber Fabrication | D25: Canada | E25: Signature structures and complex engineered timber fabrication | F25: Early Design Assist — connect in Schematic Design phase where structural input is most valuable | G25: unknown | H25: high | I25: Engineer-fabricators, not just suppliers; specialize in complex structural geometries | J25: Ecosystem Analysis PDF
A26: Sterling Structural | B26: Mass Timber | C26: CLT | D26: Illinois, USA | E26: TerraLam CLT (industrial matting transitioning to building structures) | F26: Industrial-to-Architectural Bridge — introduce to architectural community as robust industrial-grade option | G26: unknown | H26: medium | I26: Newer entrant moving from industrial to architectural markets | J26: Ecosystem Analysis PDF
A27: Kalesnikoff | B27: Mass Timber | C27: Mass Timber / Glulam | D27: Canada | E27: High-quality mass timber and glulam (multi-generational family company) | F27: Curated Quality — target high-end residential and boutique commercial architects | G27: unknown | H27: medium | I27: Multi-generational family timber company; focus on high aesthetic quality and custom fabrication | J27: Ecosystem Analysis PDF
... A135: Unitized fabricator (generic) | B135: Glazing / Curtain Wall | C135: Aluminum Backpan | D135: USA | E135: Factory aluminum backpan for unitized assemblies | F135: Specification Security | G135: yes | H135: high | I135: EPD #EPD 104.1 (Aluminum Association NA Extrusions); GWP 16 kgCO2e/kg; generic fabricator category | J135: EWS Manufacturers PDF
